nextract/__init__.py
nextract/agent_runner.py
nextract/cli.py
nextract/config.py
nextract/core.py
nextract/files.py
nextract/logging.py
nextract/mimetypes_map.py
nextract/pricing.py
nextract/prompts.py
nextract/schema.py
nextract-0.1.1.dist-info/licenses/LICENSE
nextract-0.1.1.dist-info/METADATA
nextract-0.1.1.dist-info/WHEEL
nextract-0.1.1.dist-info/entry_points.txt
nextract-0.1.1.dist-info/top_level.txt
nextract-0.1.1.dist-info/RECORD
