Metadata-Version: 2.4
Name: nextract
Version: 0.1.1
Summary: Structured extraction framework over Pydantic AI Agent with JSON Schema & Pydantic model outputs.
Author-email: Saksham Mittal <saksham.mittal@nexla.com>
License-Expression: MIT
Classifier: Programming Language :: Python :: 3
Classifier: Programming Language :: Python :: 3.10
Classifier: Programming Language :: Python :: 3.11
Classifier: Programming Language :: Python :: 3.12
Classifier: Operating System :: OS Independent
Requires-Python: >=3.10
License-File: LICENSE
Requires-Dist: pydantic>=2.7
Requires-Dist: pydantic-ai>=1.0.0
Requires-Dist: jsonschema>=4.19
Requires-Dist: structlog>=24.1.0
Requires-Dist: typer>=0.12.0
Requires-Dist: tenacity>=8.2.3
Requires-Dist: rich>=13.7
Provides-Extra: dev
Requires-Dist: mypy>=1.7; extra == "dev"
Requires-Dist: pytest>=7.0.0; extra == "dev"
Requires-Dist: pytest-mock>=3.0.0; extra == "dev"
Requires-Dist: ruff>=0.1.0; extra == "dev"
Dynamic: license-file
